Metadata-Version: 2.1
Name: pySuperfish
Version: 0.1.1
Home-page: https://github.com/ChristopherMayes/PySuperfish
Requires-Python: >=3.7
License-File: LICENSE
